{
    "baseUrl": [
        {
            "head": "http://",
            "IP":"192.168.158.120:",
            "port": "8080",
            "footer": "/appform/ws/"
        }
    ],
    "appform_top":"/apps/jhappform/",
    "jhscheduler_top":"/apps/unischeduler/",
    "login": [
        {
            "no":"001",
            "username": "GKKb%2boPTGWGyqWBbijvjCQ%3d%3d",
            "password": "GKKb%2boPTGWGyqWBbijvjCQ%3d%3d",
            "expect": "1"
        },
        {
            "no":"002",
            "username": "jhadmin",
            "password": "jhadmin",
            "expect": "0"
        },
        {
            "no":"003",
            "username": "user1",
            "password": "Letmein123",
            "expect": "0"
        },
        {
            "no":"004",
            "username": "xiao",
            "password": "jhadmin",
            "expect": "0"
        },
        {
            "no":"005",
            "username": "jhadmin",
            "password": "pps",
            "expect": "0"
        }
       
    ],
    "logout": [
        {
            "no":"006",
            "token": "ERADDDDDDDDDDDDDDDDDD90",
            "expect": "0"
        },
        {
            "no":"007",
            "token": "jhadmin",
            "expect": "0"
        },
        {
            "no":"008",
            "token": " ",
            "expect": "0"
        }
    ],
    "copyfile": [
        {
            "no":"009",
            "old_file": "protal_备份",
            "expect": "1"
        }
    ],
   "renamefile":[
         {
            "no":"010",
            "old_file_name": "portal.log",
            "new_file_name": "portal.log.bak",
            "expect":"1"
        },
        {
            "no":"011",
            "old_file_name": "txt.log",
            "new_file_name": "txt.log.bak",
            "expect": "1"
        }
    ]
}
